[
    { "id" : 0 ,"imageid": 0, "name": "Fran", "email": "fran@email.com" },
    { "id" : 1 ,"imageid": 1, "name": "Juan", "email": "juan@gmail.com" },
    { "id" : 2 ,"imageid": 2, "name": "JC", "email": "jc@gmail.com" },
    { "id" : 3 ,"imageid": 3, "name": "Alex", "email": "alex@gmail.com" },
    { "id" : 4 ,"imageid": 4, "name": "Carlos", "email": "carlos@gmail.com" },
    { "id" : 5 ,"imageid": 5, "name": "Nacho", "email": "nacho@gmail.com" },
    { "id" : 6 ,"imageid": 6, "name": "Jose", "email": "ana@gmail.com" },
    { "id" : 7 ,"imageid": 7, "name": "Tower", "email": "tower@gmail.com" },
    { "id" : 8 ,"imageid": 8, "name": "cama", "email": "cama@gmail.com" },
    { "id" : 9 ,"imageid": 9, "name": "jotase", "email": "jotase@gmail.com" }
]